liblinker
