Metadata-Version: 1.0
Name: liblinker
Version: 1.1.1
Summary: Organize your music library without altering the original directory.
Home-page: https://github.com/btym/liblinker
Author: Kevin Hogeland
Author-email: kevin@hoge.land
License: MIT
Platform: UNKNOWN
